<instance version="4" description="" template="ebps">
	<list name="extensions">
		<template_reference name="exts" value="ebpextensions\entity_blueprint_ext" List.ItemID="347108419" List.ParentItemID="347108419">
			<file name="alternate_sua" value="" overrideParent="True" />
			<bool name="browsable_in_editor" value="True" overrideParent="True" />
		</template_reference>
		<template_reference name="exts" value="ebpextensions\health_ext" List.ItemID="-894120277" List.ParentItemID="-894120277">
			<bool name="can_repair" value="True" overrideParent="True" />
			<enum_table name="armor_scaler_by_damage_type">
				<float name="Ranged" value="50" overrideParent="True" />
			</enum_table>
		</template_reference>
		<template_reference name="exts" value="ebpextensions\site_ext" List.ItemID="964116860" List.ParentItemID="964116860">
			<bool name="snap_to_construction_grid" value="True" overrideParent="True" />
		</template_reference>
		<template_reference name="exts" value="ebpextensions\type_ext" List.ItemID="519261965" List.ParentItemID="519261965">
			<list name="unit_type_list" overrideParent="True">
				<enum name="unit_type" value="building" List.ItemID="1611743729" />
				<enum name="unit_type" value="hq" List.ItemID="925822670" />
				<enum name="unit_type" value="town_center" List.ItemID="1702043946" />
				<enum name="unit_type" value="resource_drop_off" List.ItemID="796497802" />
				<enum name="unit_type" value="siegeable" List.ItemID="1517863045" />
				<enum name="unit_type" value="emits_herding_interest" List.ItemID="1109258341" />
				<enum name="unit_type" value="town_bell_target" List.ItemID="-1549469188" />
				<enum name="unit_type" value="production_building" List.ItemID="-1215155621" />
				<enum name="unit_type" value="town_center_non_capital" List.ItemID="-436598377" />
				<enum name="unit_type" value="has_default_building_weapons" List.ItemID="86901576" />
				<enum name="unit_type" value="land_food_deposit_4_by_4" List.ItemID="921365003" />
			</list>
			<list name="race_type_list" overrideParent="True">
				<instance_reference name="race_type" value="racebps\hre_ha_01" overrideParent="True" List.ItemID="-1371880848" />
			</list>
			<enum_table name="weapon_category_targeting_filter">
				<bool name="1melee" value="False" overrideParent="True" />
				<bool name="2ranged" value="False" overrideParent="True" />
				<bool name="8dummy" value="False" overrideParent="True" />
			</enum_table>
		</template_reference>
		<template_reference name="exts" value="ebpextensions\ability_ext" List.ItemID="565171784" List.ParentItemID="565171784">
			<list name="abilities" overrideParent="True">
				<instance_reference name="ability" value="abilities\timed_abilities\civ_core\core_building_scuttle" List.ItemID="-438965897" />
				<instance_reference name="ability" value="abilities\modal_abilities\core\age_up_feudal" List.ItemID="-894827720" />
				<instance_reference name="ability" value="abilities\modal_abilities\core\age_up_castle" overrideParent="True" List.ItemID="962771654" />
				<instance_reference name="ability" value="abilities\modal_abilities\core\age_up_imperial" overrideParent="True" List.ItemID="-1384529246" />
				<instance_reference name="ability" value="abilities\modal_abilities\core\town_bell\hold_return_to_work" List.ItemID="1763737258" />
				<instance_reference name="ability" value="abilities\modal_abilities\core\town_bell\global_return_to_work" List.ItemID="1424181724" />
				<instance_reference name="ability" value="abilities\timed_abilities\hre\influence_auto_repair_hre" List.ItemID="-830547247" />
				<instance_reference name="ability" value="abilities\always_on_abilities\hre\passives\influence_auto_repair_buff_tc_hre" List.ItemID="787165171" />
				<instance_reference name="ability" value="abilities\toggle_abilities\civ_core\core_xbox_auto_train_villager" mod="67987bbc33214c57b0617d9356614825" List.ItemID="1336366228" />
				<instance_reference name="ability" value="abilities\modal_abilities\core\town_bell\town_center_town_bell" List.ItemID="-1254871356" />
			</list>
		</template_reference>
		<template_reference name="exts" value="ebpextensions\construction_ext" List.ItemID="2068490625" List.ParentItemID="2068490625">
			<group name="on_construction_complete_state_tree_refs">
				<string name="while_construction_complete_entity_state_tree_ref" value="town_center_construction_complete_hre" overrideParent="True" />
			</group>
		</template_reference>
		<template_reference name="exts" value="ebpextensions\cost_ext" List.ItemID="268370002" List.ParentItemID="268370002">
			<group name="time_cost">
				<float name="time_seconds" value="120" overrideParent="True" />
			</group>
		</template_reference>
		<template_reference name="exts" value="ebpextensions\ui_ext" List.ItemID="-272167440" List.ParentItemID="-272167440">
			<instance_reference name="district_info" value="" overrideParent="True" />
			<list name="ui_extra_infos" overrideParent="True">
				<template_reference name="ui_extra_info" value="info\ui_extra_info" List.ItemID="583646886">
					<file name="icon" value="influence_decorator" overrideParent="True" />
					<locstring name="description" value="0" />
					<template_reference name="description_formatter" value="ui_text_formatter" overrideParent="True">
						<list name="formatter_arguments">
							<int name="int_value" value="200" List.ItemID="1214165034" />
						</list>
						<locstring name="formatter" value="11204532" />
					</template_reference>
				</template_reference>
			</list>
		</template_reference>
		<template_reference name="exts" value="ebpextensions\action_apply_ext" List.ItemID="1529303587" List.ParentItemID="1529303587">
			<list name="action_state_trees_run_once">
				<group name="container" List.ItemID="-2022379606" List.ListAction="Append">
					<string name="state_tree" value="building_action_apply\buildings\town_center_action_apply\set_civ_dynamic_root\hre_ha_01" overrideParent="True" />
				</group>
			</list>
		</template_reference>
		<template_reference name="exts" value="ebpextensions\spawner_ext" List.ItemID="-1875812947" List.ParentItemID="-1875812947">
			<list name="spawn_items" overrideParent="True">
				<group name="spawn_item" List.ItemID="1728046919">
					<instance_reference name="entity" value="" />
					<instance_reference name="squad" value="sbps\races\hre_ha_01\unit_villager_1_hre_ha_01" overrideParent="True" />
					<bool name="spawn_at_map_entry_point" value="False" />
					<group name="ui_position">
						<int name="ui_position_row" value="1" />
						<int name="ui_position_column" value="1" />
					</group>
					<instance_reference name="ui_menu" value="" />
					<int name="number_to_spawn" value="1" />
					<enum_table name="item_cost_adjustment">
						<float name="action" value="0" />
						<float name="command" value="0" />
						<float name="popcap" value="0" />
						<float name="food" value="0" />
						<float name="wood" value="0" />
						<float name="stone" value="0" />
						<float name="gold" value="0" />
						<float name="militia_hre" value="0" />
						<float name="merc_byz" value="0" />
					</enum_table>
					<locstring name="ui_screen_name" value="0" />
					<locstring name="ui_help_text" value="0" />
					<bool name="can_be_cancelled" value="True" />
					<int name="number_to_queue_up_to_when_modified" value="5" />
					<list name="additional_squads">
					</list>
					<instance_reference name="hotkey_binding" value="hotkeys\hotkey_binding\building_town_center\train_villager" overrideParent="True" />
					<template_reference name="ui_info_extended" value="tables\ui_info_ext" overrideParent="True">
						<template_reference name="command_card_info" value="">
						</template_reference>
						<template_reference name="quick_abilities_info" value="">
						</template_reference>
						<template_reference name="quick_commands_info" value="ui_quick_commands_info">
							<int name="quick_commands_slot_index" value="0" />
							<enum name="quick_commands_hotkey" value="x_quick_command_y" />
							<int name="quick_commands_priority" value="4" />
						</template_reference>
						<template_reference name="quick_formation_info" value="">
						</template_reference>
						<template_reference name="ping_menu_info" value="">
						</template_reference>
						<enum name="category" value="Economic" />
						<template_reference name="quick_commands_launch_hud_info" value="ui_quick_commands_launch_hud_info">
							<enum name="quick_commands_hotkey" value="x_quick_command_y" />
							<int name="quick_commands_priority" value="5" />
							<int name="quick_commands_slot_index" value="2" />
							<enum name="quick_commands_hold_time" value="quick_command_hold_time" />
						</template_reference>
						<template_reference name="relic_radial_menu_info" value="relic_radial_menu\relic_radial_menu_info">
							<instance_reference name="menu" value="relic_radial_menu\relic_radial_menu\default" />
							<int name="nominal_index" value="0" />
							<int name="priority" value="0" />
							<instance_reference name="linked" value="" />
						</template_reference>
						<enum name="observer_type" value="Disabled" />
						<group name="issuable_info">
							<bool name="is_secondary" value="False" />
							<instance_reference name="secondary_issuable" value="" />
						</group>
					</template_reference>
					<string name="ui_tooltip_data_template" value="" />
					<file name="ui_icon_name" value="" />
				</group>
				<group name="spawn_item" List.ItemID="483076999">
					<instance_reference name="entity" value="" />
					<instance_reference name="squad" value="sbps\races\hre_ha_01\unit_scout_1_hre_ha_01" overrideParent="True" />
					<bool name="spawn_at_map_entry_point" value="False" />
					<group name="ui_position">
						<int name="ui_position_row" value="1" />
						<int name="ui_position_column" value="2" />
					</group>
					<instance_reference name="ui_menu" value="" />
					<int name="number_to_spawn" value="1" />
					<enum_table name="item_cost_adjustment">
						<float name="action" value="0" />
						<float name="command" value="0" />
						<float name="popcap" value="0" />
						<float name="food" value="0" />
						<float name="wood" value="0" />
						<float name="stone" value="0" />
						<float name="gold" value="0" />
						<float name="militia_hre" value="0" />
						<float name="merc_byz" value="0" />
					</enum_table>
					<locstring name="ui_screen_name" value="0" />
					<locstring name="ui_help_text" value="0" />
					<bool name="can_be_cancelled" value="True" />
					<int name="number_to_queue_up_to_when_modified" value="5" />
					<list name="additional_squads">
					</list>
					<instance_reference name="hotkey_binding" value="hotkeys\hotkey_binding\building_town_center\train_scout" overrideParent="True" />
					<template_reference name="ui_info_extended" value="tables\ui_info_ext" overrideParent="True">
						<template_reference name="command_card_info" value="">
						</template_reference>
						<template_reference name="quick_abilities_info" value="">
						</template_reference>
						<template_reference name="quick_commands_info" value="ui_quick_commands_info">
							<int name="quick_commands_slot_index" value="1" />
							<enum name="quick_commands_hotkey" value="x_quick_command_x" />
							<int name="quick_commands_priority" value="4" />
						</template_reference>
						<template_reference name="quick_formation_info" value="">
						</template_reference>
						<template_reference name="ping_menu_info" value="">
						</template_reference>
						<enum name="category" value="Economic" />
						<template_reference name="quick_commands_launch_hud_info" value="ui_quick_commands_launch_hud_info">
							<enum name="quick_commands_hotkey" value="" />
							<int name="quick_commands_priority" value="-1" />
							<int name="quick_commands_slot_index" value="-1" />
							<enum name="quick_commands_hold_time" value="quick_command_hold_time" />
						</template_reference>
						<template_reference name="relic_radial_menu_info" value="relic_radial_menu\relic_radial_menu_info">
							<instance_reference name="menu" value="relic_radial_menu\relic_radial_menu\default" />
							<int name="nominal_index" value="4" />
							<int name="priority" value="0" />
							<instance_reference name="linked" value="" />
						</template_reference>
						<enum name="observer_type" value="Disabled" />
						<group name="issuable_info">
							<bool name="is_secondary" value="False" />
							<instance_reference name="secondary_issuable" value="" />
						</group>
					</template_reference>
					<string name="ui_tooltip_data_template" value="" />
					<file name="ui_icon_name" value="" />
				</group>
				<group name="spawn_item" comment="Monk&#xD;&#xA;" List.ItemID="1466096479">
					<group name="ui_position">
						<int name="ui_position_row" value="1" />
						<int name="ui_position_column" value="3" />
					</group>
					<instance_reference name="entity" value="" />
					<instance_reference name="squad" value="sbps\races\hre_ha_01\unit_monk_1_hre_ha_01" mod="67987bbc33214c57b0617d9356614825" overrideParent="True" />
					<bool name="spawn_at_map_entry_point" value="False" />
					<instance_reference name="ui_menu" value="" />
					<int name="number_to_spawn" value="1" />
					<enum_table name="item_cost_adjustment">
						<float name="action" value="0" />
						<float name="command" value="0" />
						<float name="popcap" value="0" />
						<float name="food" value="0" />
						<float name="wood" value="0" />
						<float name="stone" value="0" />
						<float name="gold" value="0" />
						<float name="militia_hre" value="0" />
						<float name="merc_byz" value="0" />
					</enum_table>
					<locstring name="ui_screen_name" value="0" />
					<locstring name="ui_help_text" value="0" />
					<bool name="can_be_cancelled" value="True" />
					<int name="number_to_queue_up_to_when_modified" value="5" />
					<list name="additional_squads">
					</list>
					<instance_reference name="hotkey_binding" value="hotkeys\hotkey_binding\building_town_center\train_prelate" overrideParent="True" />
					<template_reference name="ui_info_extended" value="tables\ui_info_ext" overrideParent="True">
						<template_reference name="command_card_info" value="ui_command_card_info">
							<group name="ui_position">
								<int name="ui_position_row" value="1" />
								<int name="ui_position_column" value="3" />
							</group>
							<int name="command_card_priority" value="1" />
						</template_reference>
						<template_reference name="quick_abilities_info" value="">
						</template_reference>
						<template_reference name="quick_commands_info" value="" overrideParent="True">
						</template_reference>
						<template_reference name="quick_formation_info" value="">
						</template_reference>
						<template_reference name="ping_menu_info" value="">
						</template_reference>
						<enum name="category" value="Economic" />
						<template_reference name="quick_commands_launch_hud_info" value="ui_quick_commands_launch_hud_info">
							<enum name="quick_commands_hotkey" value="" />
							<int name="quick_commands_priority" value="-1" />
							<int name="quick_commands_slot_index" value="-1" />
							<enum name="quick_commands_hold_time" value="quick_command_hold_time" />
						</template_reference>
						<template_reference name="relic_radial_menu_info" value="relic_radial_menu\relic_radial_menu_info" overrideParent="True">
							<instance_reference name="menu" value="relic_radial_menu\relic_radial_menu\default" overrideParent="True" />
							<int name="nominal_index" value="14" overrideParent="True" />
							<int name="priority" value="0" />
							<instance_reference name="linked" value="" />
						</template_reference>
						<enum name="observer_type" value="Disabled" />
						<group name="issuable_info">
							<bool name="is_secondary" value="False" />
							<instance_reference name="secondary_issuable" value="" />
						</group>
					</template_reference>
					<string name="ui_tooltip_data_template" value="" />
					<file name="ui_icon_name" value="" />
				</group>
			</list>
		</template_reference>
		<template_reference name="exts" value="ebpextensions\upgrade_ext" List.ItemID="-2049432204" List.ParentItemID="-2049432204">
			<list name="standard_upgrades" overrideParent="True">
				<instance_reference name="upgrade" value="upgrade\races\common\research\upgrade_villager_health" List.ItemID="1519000074" />
			</list>
		</template_reference>
		<template_reference name="exts" value="ebpextensions\requirement_ext" List.ItemID="-151977967" List.ParentItemID="-151977967">
			<list name="requirement_table" overrideParent="True">
				<template_reference name="required" value="requirements\required_player_upgrade" List.ItemID="1697566889">
					<enum name="reason" value="usage" overrideParent="True" />
					<locstring name="ui_name" value="0" />
					<bool name="is_present" value="True" />
					<int name="max_completed" value="100" />
					<int name="min_completed" value="1" />
					<instance_reference name="upgrade_name" value="upgrade\dev\ages\feudal_age" overrideParent="True" />
					<bool name="include_queued" value="False" />
					<group name="include_pbg_parenting">
						<bool name="include_child_pbgs" value="False" />
						<bool name="include_parent_pbgs" value="False" />
					</group>
					<bool name="include_completed" value="True" />
				</template_reference>
				<template_reference name="required" value="requirements\required_statemodelfloat" List.ItemID="-833584834">
					<locstring name="ui_name" value="0" />
					<enum name="reason" value="usage_and_display" overrideParent="True" />
					<enum name="key" value="has_capital" overrideParent="True" />
					<enum name="data_source_type" value="player_datasource" overrideParent="True" />
					<float name="default_value" value="0" />
					<float name="compare_to_value" value="1" overrideParent="True" />
					<enum name="comparison" value="equal_to" />
					<float name="ui_max_value" value="0" />
					<float name="ui_min_value" value="0" />
				</template_reference>
			</list>
		</template_reference>
		<template_reference name="exts" value="ebpextensions\statemodel_ext" List.ItemID="-1383350114" List.ParentItemID="-1383350114">
			<instance_reference name="schema" value="statemodel_schema\buildings\civilizations\hre\town_center_hre" overrideParent="True" />
		</template_reference>
		<template_reference name="exts" value="ebpextensions\tier_ext" List.ItemID="-489536604" List.ListAction="Append">
			<list name="tier_group_list">
				<list name="tier_group" List.ItemID="-1159325403">
					<group name="tier" List.ItemID="318586576">
						<list name="tier_requirements">
						</list>
						<instance_reference name="attachments" value="attachments\attachment_lists\civilizations\hre\buildings\town_center_hre\tier1_town_center_control_hre" />
						<template_reference name="statetree_tier_reached_actions" value="state_tree_reference_info">
							<state_tree_node name="ActionTree_OpeningBranch" value="" />
							<bool name="start_suspended" value="False" />
						</template_reference>
						<instance_reference name="statetree_tier_requirements_pbg" value="" />
						<instance_reference name="statetree_tier_pgb_upgrade_target_entity" value="" />
						<instance_reference name="statetree_tier_pgb_upgrade_target_squad" value="" />
						<string name="tier_attachment_action" value="" />
						<template_reference name="blueprint_conversion_parameters" value="blueprint_conversion_parameters">
							<bool name="reissue_commands" value="False" />
							<bool name="continue_state_trees" value="False" />
							<bool name="remove_from_pending_deaths" value="False" />
							<bool name="enable_all_extensions" value="True" />
						</template_reference>
						<string name="inventory_category_to_refresh_on_tier_up" value="" />
					</group>
					<group name="tier" List.ItemID="173306013">
						<list name="tier_requirements">
							<template_reference name="requirement" value="requirements\required_player_upgrade" List.ItemID="750581021">
								<enum name="reason" value="usage" />
								<locstring name="ui_name" value="0" />
								<bool name="is_present" value="True" />
								<int name="max_completed" value="100" />
								<int name="min_completed" value="1" />
								<instance_reference name="upgrade_name" value="upgrade\dev\ages\feudal_age" />
								<bool name="include_queued" value="False" />
								<group name="include_pbg_parenting">
									<bool name="include_child_pbgs" value="False" />
									<bool name="include_parent_pbgs" value="False" />
								</group>
								<bool name="include_completed" value="True" />
							</template_reference>
						</list>
						<instance_reference name="attachments" value="attachments\attachment_lists\civilizations\hre\buildings\town_center_hre\tier2_town_center_control_hre" />
						<template_reference name="statetree_tier_reached_actions" value="state_tree_reference_info">
							<state_tree_node name="ActionTree_OpeningBranch" value="" />
							<bool name="start_suspended" value="False" />
						</template_reference>
						<instance_reference name="statetree_tier_requirements_pbg" value="upgrade\dev\ages\feudal_age" />
						<instance_reference name="statetree_tier_pgb_upgrade_target_entity" value="" />
						<instance_reference name="statetree_tier_pgb_upgrade_target_squad" value="" />
						<string name="tier_attachment_action" value="act_set_current_age_feudal" overrideParent="True" />
						<template_reference name="blueprint_conversion_parameters" value="blueprint_conversion_parameters">
							<bool name="reissue_commands" value="False" />
							<bool name="continue_state_trees" value="False" />
							<bool name="remove_from_pending_deaths" value="False" />
							<bool name="enable_all_extensions" value="True" />
						</template_reference>
						<string name="inventory_category_to_refresh_on_tier_up" value="" />
					</group>
					<group name="tier" List.ItemID="-1174440366">
						<list name="tier_requirements">
							<template_reference name="requirement" value="requirements\required_player_upgrade" List.ItemID="62175918">
								<enum name="reason" value="usage" />
								<locstring name="ui_name" value="0" />
								<bool name="is_present" value="True" />
								<int name="max_completed" value="100" />
								<int name="min_completed" value="1" />
								<instance_reference name="upgrade_name" value="upgrade\dev\ages\castle_age" />
								<bool name="include_queued" value="False" />
								<group name="include_pbg_parenting">
									<bool name="include_child_pbgs" value="False" />
									<bool name="include_parent_pbgs" value="False" />
								</group>
								<bool name="include_completed" value="True" />
							</template_reference>
						</list>
						<instance_reference name="attachments" value="attachments\attachment_lists\civilizations\hre\buildings\town_center_hre\tier3_town_center_control_hre" />
						<template_reference name="statetree_tier_reached_actions" value="state_tree_reference_info">
							<state_tree_node name="ActionTree_OpeningBranch" value="" />
							<bool name="start_suspended" value="False" />
						</template_reference>
						<instance_reference name="statetree_tier_requirements_pbg" value="upgrade\dev\ages\castle_age" />
						<instance_reference name="statetree_tier_pgb_upgrade_target_entity" value="" />
						<instance_reference name="statetree_tier_pgb_upgrade_target_squad" value="" />
						<string name="tier_attachment_action" value="act_set_current_age_castle" overrideParent="True" />
						<template_reference name="blueprint_conversion_parameters" value="blueprint_conversion_parameters">
							<bool name="reissue_commands" value="False" />
							<bool name="continue_state_trees" value="False" />
							<bool name="remove_from_pending_deaths" value="False" />
							<bool name="enable_all_extensions" value="True" />
						</template_reference>
						<string name="inventory_category_to_refresh_on_tier_up" value="" />
					</group>
					<group name="tier" List.ItemID="768729615">
						<list name="tier_requirements">
							<template_reference name="requirement" value="requirements\required_player_upgrade" List.ItemID="360697907">
								<enum name="reason" value="usage" />
								<locstring name="ui_name" value="0" />
								<bool name="is_present" value="True" />
								<int name="max_completed" value="100" />
								<int name="min_completed" value="1" />
								<instance_reference name="upgrade_name" value="upgrade\dev\ages\imperial_age" />
								<bool name="include_queued" value="False" />
								<group name="include_pbg_parenting">
									<bool name="include_child_pbgs" value="False" />
									<bool name="include_parent_pbgs" value="False" />
								</group>
								<bool name="include_completed" value="True" />
							</template_reference>
						</list>
						<instance_reference name="attachments" value="attachments\attachment_lists\civilizations\hre\buildings\town_center_hre\tier4_town_center_control_hre" />
						<template_reference name="statetree_tier_reached_actions" value="state_tree_reference_info">
							<state_tree_node name="ActionTree_OpeningBranch" value="" />
							<bool name="start_suspended" value="False" />
						</template_reference>
						<instance_reference name="statetree_tier_requirements_pbg" value="upgrade\dev\ages\imperial_age" />
						<instance_reference name="statetree_tier_pgb_upgrade_target_entity" value="" />
						<instance_reference name="statetree_tier_pgb_upgrade_target_squad" value="" />
						<string name="tier_attachment_action" value="act_set_current_age_imperial" overrideParent="True" />
						<template_reference name="blueprint_conversion_parameters" value="blueprint_conversion_parameters">
							<bool name="reissue_commands" value="False" />
							<bool name="continue_state_trees" value="False" />
							<bool name="remove_from_pending_deaths" value="False" />
							<bool name="enable_all_extensions" value="True" />
						</template_reference>
						<string name="inventory_category_to_refresh_on_tier_up" value="" />
					</group>
				</list>
				<list name="tier_group" overrideParent="True" List.ItemID="1270112153">
					<group name="tier" List.ItemID="-726488099">
						<list name="tier_requirements">
						</list>
						<instance_reference name="attachments" value="attachments\attachment_lists\civilizations\english\outskirts\general\towncenter_01" comment="Outskirts go here. Removed until a fix for selection is in. To add back, copy and paste the following into this field:&#xD;&#xA;&#xD;&#xA;&lt;instance_reference name=&quot;attachments&quot; value=&quot;attachments\attachment_lists\civilizations\english\outskirts\general\towncenter_01&quot; /&gt;" overrideParent="True" />
						<template_reference name="statetree_tier_reached_actions" value="state_tree_reference_info">
							<state_tree_node name="ActionTree_OpeningBranch" value="" />
							<bool name="start_suspended" value="False" />
						</template_reference>
						<instance_reference name="statetree_tier_requirements_pbg" value="" />
						<instance_reference name="statetree_tier_pgb_upgrade_target_entity" value="" />
						<instance_reference name="statetree_tier_pgb_upgrade_target_squad" value="" />
						<string name="tier_attachment_action" value="" />
						<template_reference name="blueprint_conversion_parameters" value="blueprint_conversion_parameters">
							<bool name="reissue_commands" value="False" />
							<bool name="continue_state_trees" value="False" />
							<bool name="remove_from_pending_deaths" value="False" />
							<bool name="enable_all_extensions" value="True" />
						</template_reference>
						<string name="inventory_category_to_refresh_on_tier_up" value="" />
					</group>
					<group name="tier" List.ItemID="-525631031">
						<list name="tier_requirements">
							<template_reference name="requirement" value="requirements\required_player_upgrade" List.ItemID="301638921">
								<enum name="reason" value="usage" />
								<locstring name="ui_name" value="0" />
								<bool name="is_present" value="True" />
								<int name="max_completed" value="100" />
								<int name="min_completed" value="1" />
								<instance_reference name="upgrade_name" value="upgrade\dev\ages\castle_age" />
								<bool name="include_queued" value="False" />
								<group name="include_pbg_parenting">
									<bool name="include_child_pbgs" value="False" />
									<bool name="include_parent_pbgs" value="False" />
								</group>
								<bool name="include_completed" value="True" />
							</template_reference>
						</list>
						<instance_reference name="attachments" value="attachments\attachment_lists\civilizations\english\outskirts\general\towncenter_03" comment="Outskirts go here. Removed until a fix for selection is in. To add back, copy and paste the following into this field:&#xD;&#xA;&#xD;&#xA;&lt;instance_reference name=&quot;attachments&quot; value=&quot;attachments\attachment_lists\civilizations\english\outskirts\general\towncenter_03&quot; /&gt;" overrideParent="True" />
						<template_reference name="statetree_tier_reached_actions" value="state_tree_reference_info">
							<state_tree_node name="ActionTree_OpeningBranch" value="" />
							<bool name="start_suspended" value="False" />
						</template_reference>
						<instance_reference name="statetree_tier_requirements_pbg" value="upgrade\dev\ages\castle_age" />
						<instance_reference name="statetree_tier_pgb_upgrade_target_entity" value="" />
						<instance_reference name="statetree_tier_pgb_upgrade_target_squad" value="" />
						<string name="tier_attachment_action" value="" />
						<template_reference name="blueprint_conversion_parameters" value="blueprint_conversion_parameters">
							<bool name="reissue_commands" value="False" />
							<bool name="continue_state_trees" value="False" />
							<bool name="remove_from_pending_deaths" value="False" />
							<bool name="enable_all_extensions" value="True" />
						</template_reference>
						<string name="inventory_category_to_refresh_on_tier_up" value="" />
					</group>
				</list>
				<list name="tier_group" List.ItemID="1331045189">
					<group name="tier" List.ItemID="-408026474">
						<list name="tier_requirements">
						</list>
						<instance_reference name="attachments" value="attachments\attachment_lists\civilizations\common\buildings\building_town_center_bell_arch" />
						<template_reference name="statetree_tier_reached_actions" value="state_tree_reference_info">
							<state_tree_node name="ActionTree_OpeningBranch" value="" />
							<bool name="start_suspended" value="False" />
						</template_reference>
						<instance_reference name="statetree_tier_requirements_pbg" value="" />
						<instance_reference name="statetree_tier_pgb_upgrade_target_entity" value="" />
						<instance_reference name="statetree_tier_pgb_upgrade_target_squad" value="" />
						<string name="tier_attachment_action" value="" />
						<template_reference name="blueprint_conversion_parameters" value="blueprint_conversion_parameters">
							<bool name="reissue_commands" value="False" />
							<bool name="continue_state_trees" value="False" />
							<bool name="remove_from_pending_deaths" value="False" />
							<bool name="enable_all_extensions" value="True" />
						</template_reference>
						<string name="inventory_category_to_refresh_on_tier_up" value="" />
					</group>
				</list>
			</list>
		</template_reference>
		<template_reference name="exts" value="ebpextensions\district_generator_ext" List.ItemID="390945833" List.ListAction="Append">
			<float name="range_metres" value="32" overrideParent="True" />
			<int name="generator_value" value="0" overrideParent="True" />
			<bool name="disable_generation_on_spawn" value="False" />
			<bool name="is_root_generator" value="True" overrideParent="True" />
			<int name="district_palette_id" value="0" />
			<list name="requirements">
			</list>
		</template_reference>
		<template_reference name="exts" value="ebpextensions\district_bonuses_ext" List.ItemID="-277400689" List.ListAction="Append">
			<bool name="update_on_upgrade_changed" value="False" />
			<bool name="update_on_construction_complete" value="True" />
			<list name="district_bonuses" overrideParent="True">
				<template_reference name="district_bonus" value="district_bonus" comment="Elzbach Palace Influence" List.ItemID="-685388033">
					<template_reference name="requirement" value="options\ebpextensions\districtbonusesext\requirements\district_bonus_entity_requirement">
						<list name="dynamic_requirements">
						</list>
						<list name="satisfying_entity_groups" overrideParent="True">
							<group name="satisfying_entity_group" comment="Elzbach Palace&#xD;&#xA;" List.ItemID="1338900277">
								<list name="satisfying_entities">
									<instance_reference name="entity" value="ebps\races\hre_ha_01\buildings\building_landmark_age3_eltz_castle_hre_ha_01\building_landmark_age3_eltz_castle_hre_ha_01" mod="67987bbc33214c57b0617d9356614825" overrideParent="True" List.ItemID="647058387" />
								</list>
							</group>
						</list>
					</template_reference>
					<uniqueid name="id" value="1073741947" />
					<template_reference name="action_tree" value="state_tree_reference_info">
						<state_tree_node name="ActionTree_OpeningBranch" value="elzbach_palace_influence_bonus_hre\root" overrideParent="True" />
						<bool name="start_suspended" value="False" />
					</template_reference>
				</template_reference>
			</list>
		</template_reference>
	</list>
	<uniqueid name="pbgid" value="3039906" />
	<instance_reference name="parent_pbg" value="ebps\races\core\buildings\building_town_center" />
</instance>