<instance version="4" description="" template="ebps">
	<list name="extensions" removedIds="519464119, 397040303">
		<template_reference name="exts" value="ebpextensions\entity_blueprint_ext" List.ItemID="-315500114" List.ParentItemID="-315500114">
			<bool name="browsable_in_editor" value="True" overrideParent="True" />
			<instance_reference name="animator_attachments" value="attachments\attachment_lists\races\core\buildings\building_wonder_age1" overrideParent="True" />
		</template_reference>
		<template_reference name="exts" value="ebpextensions\health_ext" List.ItemID="125304692" List.ParentItemID="125304692">
			<bool name="can_repair" value="True" overrideParent="True" />
			<enum_table name="armor_scaler_by_damage_type">
				<float name="Fire" value="0" overrideParent="True" />
			</enum_table>
			<float name="hitpoints" value="5000" overrideParent="True" />
			<state_tree_node name="death_action_tree" value="building_death_actions\buildings\keep_death_actions" overrideParent="True" />
		</template_reference>
		<template_reference name="exts" value="ebpextensions\site_ext" List.ItemID="-962432750" List.ParentItemID="-962432750">
			<bool name="snap_to_construction_grid" value="True" overrideParent="True" />
		</template_reference>
		<template_reference name="exts" value="ebpextensions\type_ext" List.ItemID="2022824018" List.ParentItemID="2022824018">
			<list name="race_type_list" overrideParent="True">
				<instance_reference name="race_type" value="racebps\chinese" List.ItemID="141388401" />
			</list>
			<list name="unit_type_list" removedIds="495447200, 1711547619">
				<enum name="unit_type" value="military_only_production" List.ItemID="703408851" List.ListAction="Append" />
				<enum name="unit_type" value="military_production_building" List.ItemID="1092595046" List.ListAction="Append" />
			</list>
			<list name="unit_type_list_selection_keybind_only" overrideParent="True">
			</list>
		</template_reference>
		<template_reference name="exts" value="ebpextensions\construction_ext" List.ItemID="776973782" List.ParentItemID="776973782">
			<template_reference name="construction_health_option" value="options\ebpextensions\constructionext\construction_health_option">
				<float name="initial_health" value="500" overrideParent="True" />
			</template_reference>
			<string name="tooltip_data_template" value="BuildingDefensiveDataTemplate" overrideParent="True" />
			<instance_reference name="ui_range" value="" overrideParent="True" />
			<bool name="query_weapon_for_range_ui" value="False" overrideParent="True" />
			<group name="on_construction_complete_state_tree_refs">
				<string name="while_construction_complete_entity_state_tree_ref" value="building_construction_complete\buildings\keep_construction_complete" overrideParent="True" />
			</group>
		</template_reference>
		<template_reference name="exts" value="ebpextensions\cost_ext" List.ItemID="-599506936" List.ParentItemID="-599506936">
			<group name="time_cost">
				<enum_table name="cost">
					<float name="wood" value="200" overrideParent="True" />
					<float name="stone" value="200" overrideParent="True" />
				</enum_table>
				<float name="time_seconds" value="20" overrideParent="True" />
			</group>
		</template_reference>
		<template_reference name="exts" value="ebpextensions\sight_ext" overrideParent="True" List.ItemID="-785711550" List.ParentItemID="-785711550">
			<group name="detect_camouflage">
				<float name="tp_global" value="10" />
				<float name="tp_mine" value="0" />
				<float name="tp_unit" value="0" />
			</group>
			<bool name="extended_sight" value="False" />
			<float name="extended_sight_radius" value="0" />
			<float name="reveal_area_on_death_time" value="1.5" />
			<group name="sight_package">
				<float name="inner_height" value="501" overrideParent="True" />
				<float name="inner_radius" value="40" overrideParent="True" />
				<float name="outer_height" value="-15" overrideParent="True" />
				<float name="outer_radius" value="41" overrideParent="True" />
				<float name="cone_angle" value="360" />
				<float name="cone_start_radius" value="0" />
			</group>
			<list name="extended_sight_target_requirements">
			</list>
			<list name="specific_detector_actions">
			</list>
			<bool name="camouflage_detection_enabled" value="False" />
			<group name="vertical_truesight">
				<bool name="enable" value="False" />
				<float name="tolerance" value="1" />
				<float name="eye_height" value="2.5" />
			</group>
			<bool name="blockers_check_bounding_box" value="False" />
			<group name="stealth_detection">
				<bool name="enabled" value="False" />
				<float name="radius" value="0" />
				<float name="throttle" value="0" />
			</group>
		</template_reference>
		<template_reference name="exts" value="ebpextensions\ui_ext" List.ItemID="-2126635196" List.ParentItemID="-2126635196">
			<locstring name="help_text" value="778" mod="67987bbc33214c57b0617d9356614825" overrideParent="True" />
			<group name="ui_codex_info" overrideParent="True">
				<bool name="exclusive" value="False" overrideParent="True" />
				<int name="priority" value="3950" overrideParent="True" />
				<group name="ui_position">
					<int name="ui_position_column" value="-1" />
					<int name="ui_position_row" value="-1" />
				</group>
			</group>
			<list name="ui_extra_infos" overrideParent="True">
			</list>
			<file name="icon_name" value="commandery" overrideParent="True" />
			<locstring name="screen_name" value="644" mod="67987bbc33214c57b0617d9356614825" overrideParent="True" />
			<bool name="is_armoured" value="True" overrideParent="True" />
			<bool name="is_unique_to_race" value="True" overrideParent="True" />
			<string name="selection_group" value="keep22" overrideParent="True" />
			<string name="hotkey_name" value="C" overrideParent="True" />
			<file name="portrait_icon" value="races\common\buildings\keep" overrideParent="True" />
			<locstring name="extra_text" value="11143100" overrideParent="True" />
			<string name="selection_datatemplate" value="BuildingDefensiveDataTemplate" overrideParent="True" />
			<bool name="use_construction_range_on_selection" value="True" overrideParent="True" />
			<string name="telemetry_name" value="Keep" overrideParent="True" />
		</template_reference>
		<template_reference name="exts" value="ebpextensions\spawner_ext" List.ItemID="-1174991843" List.ParentItemID="-1174991843">
			<list name="spawn_items" overrideParent="True">
				<group name="spawn_item" comment="springald - castle" List.ItemID="987511103">
					<instance_reference name="entity" value="" />
					<instance_reference name="squad" value="sbps\races\chinese\clocktower\unit_springald_3_clocktower_chi" overrideParent="True" />
					<bool name="spawn_at_map_entry_point" value="False" />
					<group name="ui_position">
						<int name="ui_position_row" value="1" />
						<int name="ui_position_column" value="1" />
					</group>
					<instance_reference name="ui_menu" value="" />
					<int name="number_to_spawn" value="1" />
					<enum_table name="item_cost_adjustment">
						<float name="action" value="0" />
						<float name="command" value="0" />
						<float name="popcap" value="0" />
						<float name="food" value="0" />
						<float name="wood" value="0" />
						<float name="stone" value="0" />
						<float name="gold" value="0" />
						<float name="militia_hre" value="0" />
						<float name="merc_byz" value="0" />
					</enum_table>
					<locstring name="ui_screen_name" value="0" />
					<locstring name="ui_help_text" value="0" />
					<bool name="can_be_cancelled" value="True" />
					<int name="number_to_queue_up_to_when_modified" value="5" />
					<list name="additional_squads">
					</list>
					<instance_reference name="hotkey_binding" value="hotkeys\hotkey_binding\building_siege_workshop\produce_springald" overrideParent="True" />
					<template_reference name="ui_info_extended" value="tables\ui_info_ext">
						<template_reference name="command_card_info" value="">
						</template_reference>
						<template_reference name="quick_abilities_info" value="">
						</template_reference>
						<template_reference name="quick_commands_info" value="ui_quick_commands_info" overrideParent="True">
							<int name="quick_commands_slot_index" value="0" overrideParent="True" />
							<enum name="quick_commands_hotkey" value="x_quick_command_y" overrideParent="True" />
							<int name="quick_commands_priority" value="5" overrideParent="True" />
						</template_reference>
						<template_reference name="quick_formation_info" value="">
						</template_reference>
						<template_reference name="ping_menu_info" value="">
						</template_reference>
						<enum name="category" value="Economic" />
						<template_reference name="quick_commands_launch_hud_info" value="ui_quick_commands_launch_hud_info" overrideParent="True">
							<enum name="quick_commands_hotkey" value="x_quick_command_y" />
							<int name="quick_commands_priority" value="5" />
							<int name="quick_commands_slot_index" value="2" overrideParent="True" />
							<enum name="quick_commands_hold_time" value="quick_command_hold_time" />
						</template_reference>
						<template_reference name="relic_radial_menu_info" value="relic_radial_menu\relic_radial_menu_info" overrideParent="True">
							<instance_reference name="menu" value="relic_radial_menu\relic_radial_menu\default" />
							<int name="nominal_index" value="0" overrideParent="True" />
							<int name="priority" value="0" />
							<instance_reference name="linked" value="" />
						</template_reference>
						<enum name="observer_type" value="Disabled" />
						<group name="issuable_info">
							<bool name="is_secondary" value="False" />
							<instance_reference name="secondary_issuable" value="" />
						</group>
					</template_reference>
					<file name="ui_icon_name" value="" />
					<string name="ui_tooltip_data_template" value="" />
				</group>
				<group name="spawn_item" comment="trebuchet - imperial" List.ItemID="1408764786">
					<instance_reference name="entity" value="" />
					<instance_reference name="squad" value="sbps\races\chinese\clocktower\unit_trebuchet_4_cw_clocktower_chi" overrideParent="True" />
					<bool name="spawn_at_map_entry_point" value="False" />
					<group name="ui_position">
						<int name="ui_position_row" value="1" />
						<int name="ui_position_column" value="3" />
					</group>
					<instance_reference name="ui_menu" value="" />
					<int name="number_to_spawn" value="1" />
					<enum_table name="item_cost_adjustment">
						<float name="action" value="0" />
						<float name="command" value="0" />
						<float name="popcap" value="0" />
						<float name="food" value="0" />
						<float name="wood" value="0" />
						<float name="stone" value="0" />
						<float name="gold" value="0" />
						<float name="militia_hre" value="0" />
						<float name="merc_byz" value="0" />
					</enum_table>
					<locstring name="ui_screen_name" value="0" />
					<locstring name="ui_help_text" value="0" />
					<bool name="can_be_cancelled" value="True" />
					<int name="number_to_queue_up_to_when_modified" value="5" />
					<list name="additional_squads">
					</list>
					<instance_reference name="hotkey_binding" value="hotkeys\hotkey_binding\building_siege_workshop\produce_trebuchet" overrideParent="True" />
					<template_reference name="ui_info_extended" value="tables\ui_info_ext">
						<template_reference name="command_card_info" value="">
						</template_reference>
						<template_reference name="quick_abilities_info" value="">
						</template_reference>
						<template_reference name="quick_commands_info" value="">
						</template_reference>
						<template_reference name="quick_formation_info" value="">
						</template_reference>
						<template_reference name="ping_menu_info" value="">
						</template_reference>
						<enum name="category" value="Economic" />
						<template_reference name="quick_commands_launch_hud_info" value="ui_quick_commands_launch_hud_info">
							<enum name="quick_commands_hotkey" value="" />
							<int name="quick_commands_priority" value="-1" />
							<int name="quick_commands_slot_index" value="-1" />
							<enum name="quick_commands_hold_time" value="quick_command_hold_time" />
						</template_reference>
						<template_reference name="relic_radial_menu_info" value="relic_radial_menu\relic_radial_menu_info" overrideParent="True">
							<instance_reference name="menu" value="relic_radial_menu\relic_radial_menu\default" />
							<int name="nominal_index" value="12" overrideParent="True" />
							<int name="priority" value="0" />
							<instance_reference name="linked" value="" />
						</template_reference>
						<enum name="observer_type" value="Disabled" />
						<group name="issuable_info">
							<bool name="is_secondary" value="False" />
							<instance_reference name="secondary_issuable" value="" />
						</group>
					</template_reference>
					<file name="ui_icon_name" value="" />
					<string name="ui_tooltip_data_template" value="" />
				</group>
				<group name="spawn_item" comment="bombard - imperial + chemistry" List.ItemID="-20466165">
					<instance_reference name="entity" value="" />
					<instance_reference name="squad" value="sbps\races\chinese\clocktower\unit_bombard_4_clocktower_chi" overrideParent="True" />
					<bool name="spawn_at_map_entry_point" value="False" />
					<group name="ui_position">
						<int name="ui_position_row" value="2" overrideParent="True" />
						<int name="ui_position_column" value="1" overrideParent="True" />
					</group>
					<instance_reference name="ui_menu" value="" />
					<int name="number_to_spawn" value="1" />
					<enum_table name="item_cost_adjustment">
						<float name="action" value="0" />
						<float name="command" value="0" />
						<float name="popcap" value="0" />
						<float name="food" value="0" />
						<float name="wood" value="0" />
						<float name="stone" value="0" />
						<float name="gold" value="0" />
						<float name="militia_hre" value="0" />
						<float name="merc_byz" value="0" />
					</enum_table>
					<locstring name="ui_screen_name" value="0" />
					<locstring name="ui_help_text" value="0" />
					<bool name="can_be_cancelled" value="True" />
					<int name="number_to_queue_up_to_when_modified" value="5" />
					<list name="additional_squads">
					</list>
					<instance_reference name="hotkey_binding" value="hotkeys\hotkey_binding\building_siege_workshop\produce_bombard" overrideParent="True" />
					<template_reference name="ui_info_extended" value="tables\ui_info_ext">
						<template_reference name="command_card_info" value="">
						</template_reference>
						<template_reference name="quick_abilities_info" value="">
						</template_reference>
						<template_reference name="quick_commands_info" value="">
						</template_reference>
						<template_reference name="quick_formation_info" value="">
						</template_reference>
						<template_reference name="ping_menu_info" value="">
						</template_reference>
						<enum name="category" value="Economic" />
						<template_reference name="quick_commands_launch_hud_info" value="ui_quick_commands_launch_hud_info">
							<enum name="quick_commands_hotkey" value="" />
							<int name="quick_commands_priority" value="-1" />
							<int name="quick_commands_slot_index" value="-1" />
							<enum name="quick_commands_hold_time" value="quick_command_hold_time" />
						</template_reference>
						<template_reference name="relic_radial_menu_info" value="relic_radial_menu\relic_radial_menu_info" overrideParent="True">
							<instance_reference name="menu" value="relic_radial_menu\relic_radial_menu\default" />
							<int name="nominal_index" value="2" overrideParent="True" />
							<int name="priority" value="0" />
							<instance_reference name="linked" value="" />
						</template_reference>
						<enum name="observer_type" value="Disabled" />
						<group name="issuable_info">
							<bool name="is_secondary" value="False" />
							<instance_reference name="secondary_issuable" value="" />
						</group>
					</template_reference>
					<file name="ui_icon_name" value="" />
					<string name="ui_tooltip_data_template" value="" />
				</group>
				<group name="spawn_item" comment="Nest of Bees - Imperial + Chemistry&#xD;&#xA;" List.ItemID="323049503">
					<instance_reference name="entity" value="" />
					<instance_reference name="squad" value="sbps\races\chinese\clocktower\unit_nest_of_bees_4_clocktower_chi" overrideParent="True" />
					<bool name="spawn_at_map_entry_point" value="False" />
					<group name="ui_position">
						<int name="ui_position_row" value="1" overrideParent="True" />
						<int name="ui_position_column" value="2" overrideParent="True" />
					</group>
					<instance_reference name="ui_menu" value="" />
					<int name="number_to_spawn" value="1" />
					<enum_table name="item_cost_adjustment">
						<float name="action" value="0" />
						<float name="command" value="0" />
						<float name="popcap" value="0" />
						<float name="food" value="0" />
						<float name="wood" value="0" />
						<float name="stone" value="0" />
						<float name="gold" value="0" />
						<float name="militia_hre" value="0" />
						<float name="merc_byz" value="0" />
					</enum_table>
					<locstring name="ui_screen_name" value="0" />
					<locstring name="ui_help_text" value="0" />
					<bool name="can_be_cancelled" value="True" />
					<int name="number_to_queue_up_to_when_modified" value="5" />
					<list name="additional_squads">
					</list>
					<instance_reference name="hotkey_binding" value="hotkeys\hotkey_binding\building_siege_workshop\produce_mangonel" overrideParent="True" />
					<template_reference name="ui_info_extended" value="tables\ui_info_ext">
						<template_reference name="command_card_info" value="">
						</template_reference>
						<template_reference name="quick_abilities_info" value="">
						</template_reference>
						<template_reference name="quick_commands_info" value="ui_quick_commands_info" overrideParent="True">
							<int name="quick_commands_slot_index" value="1" overrideParent="True" />
							<enum name="quick_commands_hotkey" value="x_quick_command_x" overrideParent="True" />
							<int name="quick_commands_priority" value="5" overrideParent="True" />
						</template_reference>
						<template_reference name="quick_formation_info" value="">
						</template_reference>
						<template_reference name="ping_menu_info" value="">
						</template_reference>
						<enum name="category" value="Economic" />
						<template_reference name="quick_commands_launch_hud_info" value="ui_quick_commands_launch_hud_info">
							<enum name="quick_commands_hotkey" value="" />
							<int name="quick_commands_priority" value="-1" />
							<int name="quick_commands_slot_index" value="-1" />
							<enum name="quick_commands_hold_time" value="quick_command_hold_time" />
						</template_reference>
						<template_reference name="relic_radial_menu_info" value="relic_radial_menu\relic_radial_menu_info" overrideParent="True">
							<instance_reference name="menu" value="relic_radial_menu\relic_radial_menu\default" />
							<int name="nominal_index" value="4" overrideParent="True" />
							<int name="priority" value="0" />
							<instance_reference name="linked" value="" />
						</template_reference>
						<enum name="observer_type" value="Disabled" />
						<group name="issuable_info">
							<bool name="is_secondary" value="False" />
							<instance_reference name="secondary_issuable" value="" />
						</group>
					</template_reference>
					<file name="ui_icon_name" value="" />
					<string name="ui_tooltip_data_template" value="" />
				</group>
				<group name="spawn_item" comment="Ram - castle" List.ItemID="180405557">
					<instance_reference name="entity" value="" />
					<instance_reference name="squad" value="sbps\races\chinese\clocktower\unit_ram_3_clocktower_chi" overrideParent="True" />
					<bool name="spawn_at_map_entry_point" value="False" />
					<group name="ui_position">
						<int name="ui_position_row" value="1" />
						<int name="ui_position_column" value="4" overrideParent="True" />
					</group>
					<instance_reference name="ui_menu" value="" />
					<int name="number_to_spawn" value="1" />
					<enum_table name="item_cost_adjustment">
						<float name="action" value="0" />
						<float name="command" value="0" />
						<float name="popcap" value="0" />
						<float name="food" value="0" />
						<float name="wood" value="0" />
						<float name="stone" value="0" />
						<float name="gold" value="0" />
						<float name="militia_hre" value="0" />
						<float name="merc_byz" value="0" />
					</enum_table>
					<locstring name="ui_screen_name" value="0" />
					<locstring name="ui_help_text" value="0" />
					<bool name="can_be_cancelled" value="True" />
					<int name="number_to_queue_up_to_when_modified" value="5" />
					<list name="additional_squads">
					</list>
					<instance_reference name="hotkey_binding" value="hotkeys\hotkey_binding\building_siege_workshop\produce_ram" overrideParent="True" />
					<template_reference name="ui_info_extended" value="tables\ui_info_ext">
						<template_reference name="command_card_info" value="">
						</template_reference>
						<template_reference name="quick_abilities_info" value="">
						</template_reference>
						<template_reference name="quick_commands_info" value="">
						</template_reference>
						<template_reference name="quick_formation_info" value="">
						</template_reference>
						<template_reference name="ping_menu_info" value="">
						</template_reference>
						<enum name="category" value="Economic" />
						<template_reference name="quick_commands_launch_hud_info" value="ui_quick_commands_launch_hud_info">
							<enum name="quick_commands_hotkey" value="" />
							<int name="quick_commands_priority" value="-1" />
							<int name="quick_commands_slot_index" value="-1" />
							<enum name="quick_commands_hold_time" value="quick_command_hold_time" />
						</template_reference>
						<template_reference name="relic_radial_menu_info" value="relic_radial_menu\relic_radial_menu_info" overrideParent="True">
							<instance_reference name="menu" value="relic_radial_menu\relic_radial_menu\default" />
							<int name="nominal_index" value="8" overrideParent="True" />
							<int name="priority" value="0" />
							<instance_reference name="linked" value="" />
						</template_reference>
						<enum name="observer_type" value="Disabled" />
						<group name="issuable_info">
							<bool name="is_secondary" value="False" />
							<instance_reference name="secondary_issuable" value="" />
						</group>
					</template_reference>
					<file name="ui_icon_name" value="" />
					<string name="ui_tooltip_data_template" value="" />
				</group>
				<group name="spawn_item" List.ItemID="1057100916">
					<group name="ui_position">
						<int name="ui_position_row" value="3" overrideParent="True" />
						<int name="ui_position_column" value="1" overrideParent="True" />
					</group>
					<instance_reference name="entity" value="" />
					<instance_reference name="squad" value="sbps\races\legion\legion_chi_forbiddenarmy" mod="67987bbc33214c57b0617d9356614825" overrideParent="True" />
					<bool name="spawn_at_map_entry_point" value="False" />
					<instance_reference name="ui_menu" value="" overrideParent="True" />
					<int name="number_to_spawn" value="1" />
					<locstring name="ui_screen_name" value="0" />
					<locstring name="ui_help_text" value="0" />
					<enum_table name="item_cost_adjustment">
						<float name="action" value="0" />
						<float name="command" value="0" />
						<float name="popcap" value="0" />
						<float name="food" value="0" />
						<float name="wood" value="0" />
						<float name="stone" value="0" />
						<float name="gold" value="0" />
						<float name="militia_hre" value="0" />
						<float name="merc_byz" value="0" />
					</enum_table>
					<bool name="can_be_cancelled" value="True" />
					<int name="number_to_queue_up_to_when_modified" value="5" />
					<list name="additional_squads">
						<instance_reference name="additional_squad" value="sbps\races\chinese\unit_forbidden_spear_chi" mod="67987bbc33214c57b0617d9356614825" overrideParent="True" List.ItemID="616123555" />
						<instance_reference name="additional_squad" value="sbps\races\chinese\unit_forbidden_spear_chi" mod="67987bbc33214c57b0617d9356614825" overrideParent="True" List.ItemID="-705654655" />
						<instance_reference name="additional_squad" value="sbps\races\chinese\unit_forbidden_handcannon_chi" mod="67987bbc33214c57b0617d9356614825" overrideParent="True" List.ItemID="-835414154" />
						<instance_reference name="additional_squad" value="sbps\races\chinese\unit_forbidden_handcannon_chi" mod="67987bbc33214c57b0617d9356614825" overrideParent="True" List.ItemID="-1815802512" />
						<instance_reference name="additional_squad" value="sbps\races\chinese\unit_forbidden_handcannon_chi" mod="67987bbc33214c57b0617d9356614825" overrideParent="True" List.ItemID="-313213762" />
						<instance_reference name="additional_squad" value="sbps\races\chinese\unit_forbidden_handcannon_chi" mod="67987bbc33214c57b0617d9356614825" overrideParent="True" List.ItemID="-1833406422" />
						<instance_reference name="additional_squad" value="sbps\races\chinese\unit_forbidden_spear_chi" mod="67987bbc33214c57b0617d9356614825" overrideParent="True" List.ItemID="-2091964339" />
						<instance_reference name="additional_squad" value="sbps\races\chinese\unit_forbidden_sword_chi" mod="67987bbc33214c57b0617d9356614825" overrideParent="True" List.ItemID="1071832675" />
						<instance_reference name="additional_squad" value="sbps\races\chinese\unit_forbidden_spear_chi" mod="67987bbc33214c57b0617d9356614825" overrideParent="True" List.ItemID="1592806736" />
						<instance_reference name="additional_squad" value="sbps\races\chinese\unit_forbidden_sword_chi" mod="67987bbc33214c57b0617d9356614825" overrideParent="True" List.ItemID="227810590" />
					</list>
					<instance_reference name="hotkey_binding" value="" />
					<template_reference name="ui_info_extended" value="tables\ui_info_ext" overrideParent="True">
						<template_reference name="command_card_info" value="ui_command_card_info">
							<group name="ui_position">
								<int name="ui_position_row" value="1" />
								<int name="ui_position_column" value="3" />
							</group>
							<int name="command_card_priority" value="1" />
						</template_reference>
						<template_reference name="quick_abilities_info" value="">
						</template_reference>
						<template_reference name="quick_commands_info" value="">
						</template_reference>
						<template_reference name="quick_formation_info" value="">
						</template_reference>
						<template_reference name="ping_menu_info" value="">
						</template_reference>
						<enum name="category" value="Economic" />
						<template_reference name="quick_commands_launch_hud_info" value="ui_quick_commands_launch_hud_info">
							<enum name="quick_commands_hotkey" value="" />
							<int name="quick_commands_priority" value="-1" />
							<int name="quick_commands_slot_index" value="-1" />
							<enum name="quick_commands_hold_time" value="quick_command_hold_time" />
						</template_reference>
						<template_reference name="relic_radial_menu_info" value="relic_radial_menu\relic_radial_menu_info">
							<instance_reference name="menu" value="relic_radial_menu\relic_radial_menu\mon_improved" />
							<int name="nominal_index" value="4" overrideParent="True" />
							<int name="priority" value="0" />
							<instance_reference name="linked" value="" />
						</template_reference>
						<enum name="observer_type" value="Disabled" />
						<group name="issuable_info">
							<bool name="is_secondary" value="False" />
							<instance_reference name="secondary_issuable" value="" />
						</group>
					</template_reference>
					<string name="ui_tooltip_data_template" value="" />
					<file name="ui_icon_name" value="" />
				</group>
			</list>
			<state_tree_node name="production_item_completed_openingbranch" value="" overrideParent="True" />
			<bool name="enforce_minimum_clearance_at_spawn_positions" value="True" overrideParent="True" />
			<instance_reference name="rally_pass_type" value="pass_types\infantry" overrideParent="True" />
			<bool name="reset_production_progress_at_current_pop_cap" value="False" overrideParent="True" />
		</template_reference>
		<template_reference name="exts" value="ebpextensions\upgrade_ext" List.ItemID="-57558359" List.ParentItemID="-57558359">
			<list name="standard_upgrades" overrideParent="True">
			</list>
			<state_tree_node name="production_item_completed_openingbranch" value="building_production_item_completed_chi" overrideParent="True" />
		</template_reference>
		<template_reference name="exts" value="ebpextensions\requirement_ext" List.ItemID="-630964933" List.ParentItemID="-630964933">
			<list name="requirement_table" removedIds="-1923806473">
				<template_reference name="required" value="requirements\required_statemodelbool" overrideParent="True" List.ItemID="1492001216" List.ListAction="Append">
					<locstring name="ui_name" value="11149355" />
					<enum name="reason" value="usage" />
					<enum name="key" value="dynasty_2_was_completed_chi" />
					<enum name="data_source_type" value="self_datasource" />
					<bool name="default_value" value="False" />
					<bool name="compare_to_value" value="True" />
				</template_reference>
				<template_reference name="required" value="requirements\required_not" List.ItemID="316117951" List.ListAction="Append">
					<enum name="reason" value="usage" />
					<locstring name="ui_name" value="777" mod="67987bbc33214c57b0617d9356614825" overrideParent="True" />
					<list name="requirement_table">
						<template_reference name="required" value="requirements\required_structure" List.ItemID="-1617832288">
							<enum name="reason" value="usage" />
							<locstring name="ui_name" value="0" />
							<instance_reference name="structure_name" value="ebps\races\chinese\buildings\building_commandery_control_chi" mod="67987bbc33214c57b0617d9356614825" overrideParent="True" />
							<int name="required_structure_count" value="1" overrideParent="True" />
							<bool name="check_team" value="False" />
							<bool name="require_construction_complete" value="False" />
							<group name="include_pbg_parenting">
								<bool name="include_child_pbgs" value="False" />
								<bool name="include_parent_pbgs" value="False" />
							</group>
						</template_reference>
					</list>
				</template_reference>
			</list>
		</template_reference>
		<template_reference name="exts" value="ebpextensions\burn_ext" List.ItemID="-834591796" List.ParentItemID="-834591796">
			<float name="on_fire_damage_per_sec" value="10" overrideParent="True" />
		</template_reference>
		<template_reference name="exts" value="ebpextensions\action_apply_ext" List.ItemID="687655738" List.ParentItemID="687655738">
			<list name="action_state_trees">
				<group name="container" List.ItemID="-470518592" List.ParentItemID="-470518592">
					<string name="state_tree" value="building_action_apply\buildings\keep_action_apply" overrideParent="True" />
				</group>
			</list>
		</template_reference>
		<template_reference name="exts" value="ebpextensions\ability_ext" List.ItemID="-231398338" List.ParentItemID="-231398338">
			<list name="abilities" overrideParent="True">
				<instance_reference name="ability" value="abilities\timed_abilities\civ_core\core_building_scuttle" List.ItemID="48014398" />
				<instance_reference name="ability" value="abilities\always_on_abilities\chinese\building_generate_tax_chi" List.ItemID="-1534864744" />
			</list>
		</template_reference>
		<template_reference name="exts" value="ebpextensions\interactive_object_ext" List.ItemID="1887967718" List.ParentItemID="1887967718">
			<list name="type_list" overrideParent="True">
				<group name="type" List.ItemID="1490325159">
					<enum name="interaction_type" value="repair" />
					<int name="prefer_number" value="-1" />
					<int name="max_number" value="-1" />
					<enum name="interaction_target_type" value="entity" />
					<template_reference name="node_list_option" value="options\none">
					</template_reference>
					<bool name="block_pathing_when_interacted" value="False" />
				</group>
				<group name="type" List.ItemID="-24209914">
					<enum name="interaction_type" value="construct" />
					<int name="prefer_number" value="-1" />
					<int name="max_number" value="-1" />
					<enum name="interaction_target_type" value="entity" />
					<template_reference name="node_list_option" value="options\none">
					</template_reference>
					<bool name="block_pathing_when_interacted" value="False" />
				</group>
				<group name="type" List.ItemID="1177338200">
					<enum name="interaction_type" value="official_building_reserved_chi" overrideParent="True" />
					<int name="prefer_number" value="-1" overrideParent="True" />
					<int name="max_number" value="-1" overrideParent="True" />
					<enum name="interaction_target_type" value="entity" />
					<template_reference name="node_list_option" value="options\none">
					</template_reference>
					<bool name="block_pathing_when_interacted" value="False" />
				</group>
			</list>
		</template_reference>
		<template_reference name="exts" value="ebpextensions\statemodel_ext" List.ItemID="-1325636409" List.ParentItemID="-1325636409">
			<instance_reference name="schema" value="statemodel_schema\buildings\civilizations\chinese\keep_chi" overrideParent="True" />
		</template_reference>
		<template_reference name="exts" value="ebpextensions\animation_action_tree_ext" List.ItemID="-195300055" List.ParentItemID="-195300055">
			<bool name="use_root_motion" value="False" overrideParent="True" />
		</template_reference>
		<template_reference name="exts" value="ebpextensions\audio_ext" List.ItemID="-1114546111" List.ParentItemID="-1114546111">
			<string name="single_select_event" value="sfx_building_defense_keep_selection_play" overrideParent="True" />
			<int name="music_importance" value="40" overrideParent="True" />
			<int name="combat_importance" value="-40" overrideParent="True" />
		</template_reference>
		<template_reference name="exts" value="ebpextensions\speech_ext" List.ItemID="1175162898" List.ParentItemID="1175162898">
			<int name="importance" value="25" overrideParent="True" />
		</template_reference>
		<template_reference name="exts" value="ebpextensions\building_presentation_ext" List.ItemID="-1847099477" List.ParentItemID="-1847099477">
			<file name="construction_stamp" value="art\stamps\scaffolding\chinese_ha\chi_cont_land_a_01" overrideParent="True" />
		</template_reference>
		<template_reference name="exts" value="ebpextensions\tier_ext" overrideParent="True" List.ItemID="1935535472" List.ListAction="Append">
			<list name="tier_group_list" overrideParent="True">
				<list name="tier_group" List.ItemID="1539792343">
					<group name="tier" List.ItemID="1676768232">
						<list name="tier_requirements">
						</list>
						<instance_reference name="attachments" value="attachments\attachment_lists\civilizations\chinese_ha_01\buildings\tier1_landmark_1a_chi_ha" overrideParent="True" />
						<template_reference name="statetree_tier_reached_actions" value="state_tree_reference_info">
							<state_tree_node name="ActionTree_OpeningBranch" value="" />
							<bool name="start_suspended" value="False" />
						</template_reference>
						<instance_reference name="statetree_tier_requirements_pbg" value="" />
						<instance_reference name="statetree_tier_pgb_upgrade_target_entity" value="" />
						<instance_reference name="statetree_tier_pgb_upgrade_target_squad" value="" />
						<string name="tier_attachment_action" value="" />
						<template_reference name="blueprint_conversion_parameters" value="blueprint_conversion_parameters">
							<bool name="reissue_commands" value="False" />
							<bool name="continue_state_trees" value="False" />
							<bool name="remove_from_pending_deaths" value="False" />
							<bool name="enable_all_extensions" value="True" />
						</template_reference>
						<string name="inventory_category_to_refresh_on_tier_up" value="" />
					</group>
				</list>
				<list name="tier_group" overrideParent="True" List.ItemID="-763700767">
					<group name="tier" List.ItemID="444275511">
						<list name="tier_requirements">
						</list>
						<instance_reference name="attachments" value="attachments\attachment_lists\civilizations\chinese_ha_01\outskirts\landmarks\chi_ha_lan_01a" overrideParent="True" />
						<template_reference name="statetree_tier_reached_actions" value="state_tree_reference_info">
							<state_tree_node name="ActionTree_OpeningBranch" value="" />
							<bool name="start_suspended" value="False" />
						</template_reference>
						<instance_reference name="statetree_tier_requirements_pbg" value="" />
						<instance_reference name="statetree_tier_pgb_upgrade_target_entity" value="" />
						<instance_reference name="statetree_tier_pgb_upgrade_target_squad" value="" />
						<string name="tier_attachment_action" value="" />
						<template_reference name="blueprint_conversion_parameters" value="blueprint_conversion_parameters">
							<bool name="reissue_commands" value="False" />
							<bool name="continue_state_trees" value="False" />
							<bool name="remove_from_pending_deaths" value="False" />
							<bool name="enable_all_extensions" value="True" />
						</template_reference>
						<string name="inventory_category_to_refresh_on_tier_up" value="" />
					</group>
				</list>
			</list>
		</template_reference>
		<template_reference name="exts" value="ebpextensions\district_bonuses_ext" List.ItemID="-1285109746" List.ListAction="Append">
			<bool name="update_on_upgrade_changed" value="False" />
			<bool name="update_on_construction_complete" value="True" />
			<list name="district_bonuses" overrideParent="True">
				<template_reference name="district_bonus" value="district_bonus" comment="population" List.ItemID="-43318320">
					<template_reference name="requirement" value="options\ebpextensions\districtbonusesext\requirements\district_bonus_entity_requirement">
						<list name="dynamic_requirements" overrideParent="True">
						</list>
						<list name="satisfying_entity_groups" overrideParent="True">
							<group name="satisfying_entity_group" comment="Landmark Academy" List.ItemID="1018880887">
								<list name="satisfying_entities">
									<instance_reference name="entity" value="ebps\races\chinese\buildings\building_landmark_age1_academy_chi\building_landmark_age1_academy_control_chi" overrideParent="True" List.ItemID="-970757940" />
								</list>
							</group>
						</list>
					</template_reference>
					<uniqueid name="id" value="1073741998" />
					<template_reference name="action_tree" value="state_tree_reference_info">
						<state_tree_node name="ActionTree_OpeningBranch" value="chinese_influence" overrideParent="True" />
						<bool name="start_suspended" value="False" />
					</template_reference>
				</template_reference>
			</list>
		</template_reference>
		<template_reference name="exts" value="ebpextensions\district_generator_ext" List.ItemID="477430821" List.ListAction="Append">
			<float name="range_metres" value="0" overrideParent="True" />
			<int name="generator_value" value="0" overrideParent="True" />
			<bool name="disable_generation_on_spawn" value="False" />
			<bool name="is_root_generator" value="False" />
			<int name="district_palette_id" value="0" />
			<list name="requirements">
			</list>
		</template_reference>
	</list>
	<uniqueid name="pbgid" value="1073742430" />
	<instance_reference name="parent_pbg" value="ebps\races\core\buildings\building_defense_keep" />
</instance>