<instance version="4" description="" template="weapon">
	<group name="weapon_bag">
		<group name="damage">
			<float name="max" value="9" overrideParent="True" />
			<float name="min" value="9" overrideParent="True" />
		</group>
		<group name="range">
			<float name="max" value="18" overrideParent="True" />
		</group>
		<group name="reload">
			<group name="duration">
				<float name="max" value="1.75" overrideParent="True" />
				<float name="min" value="1.75" overrideParent="True" />
			</group>
		</group>
		<group name="burst" overrideParent="True">
			<bool name="can_burst" value="True" />
			<group name="duration">
				<float name="max" value="0.25" />
				<float name="min" value="0.25" />
			</group>
			<group name="incremental_target_table">
				<float name="accuracy_multiplier" value="0" />
				<group name="search_radius">
					<float name="far" value="0" />
					<float name="near" value="0" />
					<float name="mid" value="0" />
				</group>
			</group>
			<group name="rate_of_fire">
				<float name="max" value="9" />
				<float name="min" value="9" />
			</group>
			<group name="duration_multiplier">
				<float name="near" value="1" />
				<float name="far" value="1" />
				<float name="mid" value="1" />
			</group>
			<group name="rate_of_fire_multiplier">
				<float name="near" value="1" />
				<float name="far" value="1" />
				<float name="mid" value="1" />
			</group>
			<bool name="focus_fire" value="False" />
			<bool name="convert_target_to_position_before_firing" value="False" />
			<bool name="uninterruptible_burst_fire" value="False" />
		</group>
		<group name="moving">
			<bool name="can_fire_while_moving" value="True" overrideParent="True" />
		</group>
	</group>
	<uniqueid name="pbgid" value="9000530" />
	<instance_reference name="parent_pbg" value="weapon\races\common\ranged\weapon_horsearcher_3" />
</instance>