<instance version="4" description="Imperial Age Horseman" template="ebps">
	<list name="extensions">
		<template_reference name="exts" value="ebpextensions\entity_blueprint_ext" List.ItemID="1117396992" List.ParentItemID="1117396992">
			<bool name="browsable_in_editor" value="True" overrideParent="True" />
		</template_reference>
		<template_reference name="exts" value="ebpextensions\ability_ext" List.ItemID="1948403926" List.ParentItemID="1948403926">
			<list name="abilities" overrideParent="True">
				<instance_reference name="ability" value="abilities\always_on_abilities\ottoman\mehter_formation_ott" List.ItemID="45858996" />
			</list>
		</template_reference>
		<template_reference name="exts" value="ebpextensions\action_apply_ext" List.ItemID="43246497" List.ParentItemID="43246497">
			<list name="action_state_trees">
				<group name="container" List.ItemID="16843610" List.ParentItemID="16843610">
					<string name="state_tree" value="unit_action_apply\units\horseman\audio\sul\4" overrideParent="True" />
				</group>
			</list>
		</template_reference>
		<template_reference name="exts" value="ebpextensions\cost_ext" List.ItemID="1168881951" List.ParentItemID="1168881951">
			<group name="time_cost">
				<enum_table name="cost">
					<float name="food" value="120" overrideParent="True" />
					<float name="wood" value="40" overrideParent="True" />
				</enum_table>
				<float name="time_seconds" value="30" overrideParent="True" />
			</group>
		</template_reference>
		<template_reference name="exts" value="ebpextensions\health_ext" List.ItemID="-975825396" List.ParentItemID="-975825396">
			<float name="hitpoints" value="220" overrideParent="True" />
		</template_reference>
		<template_reference name="exts" value="ebpextensions\type_ext" List.ItemID="-809868374" List.ParentItemID="-809868374">
			<list name="unit_type_list" overrideParent="True">
				<enum name="unit_type" value="military" List.ItemID="325521833" />
				<enum name="unit_type" value="cavalry" List.ItemID="2106207415" />
				<enum name="unit_type" value="cavalry_light" List.ItemID="2143170818" />
				<enum name="unit_type" value="human" List.ItemID="2019907082" />
				<enum name="unit_type" value="horse" List.ItemID="206713314" />
				<enum name="unit_type" value="melee" List.ItemID="-1290244524" />
				<enum name="unit_type" value="formational" List.ItemID="-46933441" />
				<enum name="unit_type" value="torch_thrower" List.ItemID="427441185" />
				<enum name="unit_type" value="annihilation_condition" List.ItemID="-1647946592" />
				<enum name="unit_type" value="included_by_military_hotkeys" List.ItemID="-447364752" />
				<enum name="unit_type" value="sipahi_ott" List.ItemID="415344191" />
				<enum name="unit_type" value="find_non_siege_land_military" List.ItemID="942359633" List.ParentItemID="1478647624" />
				<enum name="unit_type" value="land_military" List.ItemID="-66601959" List.ParentItemID="2063915872" />
			</list>
			<list name="race_type_list" overrideParent="True">
				<instance_reference name="race_type" value="racebps\templar" overrideParent="True" List.ItemID="-1773186125" />
			</list>
		</template_reference>
		<template_reference name="exts" value="ebpextensions\combat_ext" List.ItemID="1065738823" List.ParentItemID="1065738823">
			<list name="hardpoints">
				<group name="hardpoint" List.ItemID="-1753816310" List.ParentItemID="-1753816310">
					<list name="weapon_table" overrideParent="True">
						<group name="weapon" List.ItemID="-1402626894">
							<group name="heading">
								<float name="x" value="0" />
								<float name="y" value="0" />
								<float name="z" value="1" />
							</group>
							<float name="length" value="0" />
							<group name="origin">
								<float name="x" value="0" />
								<float name="y" value="0" />
								<float name="z" value="0" />
							</group>
							<enum name="type" value="default" />
							<template_reference name="weapon_entity_attachment" value="" overrideParent="True">
							</template_reference>
							<template_reference name="non_entity_weapon_wrapper" value="non_entity_weapon_wrapper" overrideParent="True">
								<instance_reference name="non_entity_weapon_wrapper_pbg" value="weapon\races\ottoman\melee\weapon_horseman_4_ott" overrideParent="True" />
								<instance_reference name="animator_attachments" value="attachments\attachment_lists\races\ottoman\weapons\wpn_melee_horseman_4_ott" overrideParent="True" />
								<string name="marker_name_parent" value="metarig_rarmpalmsocket" overrideParent="True" />
							</template_reference>
						</group>
						<group name="weapon" List.ItemID="-58066910">
							<group name="heading">
								<float name="x" value="0" />
								<float name="y" value="0" />
								<float name="z" value="1" />
							</group>
							<float name="length" value="0" />
							<group name="origin">
								<float name="x" value="0" />
								<float name="y" value="0.5" />
								<float name="z" value="0" />
							</group>
							<enum name="type" value="default" />
							<template_reference name="weapon_entity_attachment" value="" overrideParent="True">
							</template_reference>
							<template_reference name="non_entity_weapon_wrapper" value="non_entity_weapon_wrapper" overrideParent="True">
								<instance_reference name="non_entity_weapon_wrapper_pbg" value="weapon\races\common\ranged\weapon_torch_horseman" overrideParent="True" />
								<instance_reference name="animator_attachments" value="attachments\attachment_lists\races\core\weapons\wpn_siege_torch_horseman" overrideParent="True" />
								<string name="marker_name_parent" value="metarig_rarmpalmsocket" overrideParent="True" />
							</template_reference>
						</group>
						<group name="weapon" List.ItemID="-1218720115">
							<group name="heading">
								<float name="x" value="0" />
								<float name="y" value="0" />
								<float name="z" value="1" />
							</group>
							<float name="length" value="0" />
							<group name="origin">
								<float name="x" value="0" />
								<float name="y" value="0.5" />
								<float name="z" value="0" />
							</group>
							<enum name="type" value="default" />
							<template_reference name="weapon_entity_attachment" value="" overrideParent="True">
							</template_reference>
							<template_reference name="non_entity_weapon_wrapper" value="non_entity_weapon_wrapper" overrideParent="True">
								<instance_reference name="non_entity_weapon_wrapper_pbg" value="weapon\races\ottoman\melee\weapon_horseman_4_charge_ott" overrideParent="True" />
								<instance_reference name="animator_attachments" value="attachments\attachment_lists\races\ottoman\weapons\wpn_melee_horseman_4_ott" overrideParent="True" />
								<string name="marker_name_parent" value="metarig_rarmpalmsocket" overrideParent="True" />
							</template_reference>
						</group>
					</list>
				</group>
			</list>
		</template_reference>
		<template_reference name="exts" value="ebpextensions\moving_ext" List.ItemID="1031827966" List.ParentItemID="1031827966">
			<enum_table name="speed_scaling_table">
				<float name="default_speed" value="7" overrideParent="True" />
			</enum_table>
		</template_reference>
		<template_reference name="exts" value="ebpextensions\speech_ext" List.ItemID="-2123647376" List.ParentItemID="-2123647376">
			<string name="speaker_code" value="sipahi" overrideParent="True" />
		</template_reference>
		<template_reference name="exts" value="ebpextensions\tier_ext" overrideParent="True" List.ItemID="-14762799" List.ParentItemID="-14762799">
			<list name="tier_group_list" overrideParent="True">
				<list name="tier_group" overrideParent="True" List.ItemID="1604341938">
					<group name="tier" List.ItemID="-1961864575">
						<list name="tier_requirements" overrideParent="True">
						</list>
						<instance_reference name="attachments" value="attachments\attachment_lists\civilizations\ottoman\units\tier4_cavalry_horseman_ott" overrideParent="True" />
						<template_reference name="statetree_tier_reached_actions" value="state_tree_reference_info">
							<state_tree_node name="ActionTree_OpeningBranch" value="tier_unit_exposure_dca" overrideParent="True" />
							<bool name="start_suspended" value="False" />
						</template_reference>
						<instance_reference name="statetree_tier_requirements_pbg" value="" />
						<instance_reference name="statetree_tier_pgb_upgrade_target_entity" value="" />
						<instance_reference name="statetree_tier_pgb_upgrade_target_squad" value="" />
						<string name="tier_attachment_action" value="" />
						<template_reference name="blueprint_conversion_parameters" value="blueprint_conversion_parameters">
							<bool name="reissue_commands" value="False" />
							<bool name="continue_state_trees" value="True" />
							<bool name="remove_from_pending_deaths" value="False" />
							<bool name="enable_all_extensions" value="True" />
						</template_reference>
						<string name="inventory_category_to_refresh_on_tier_up" value="" />
					</group>
				</list>
			</list>
		</template_reference>
		<template_reference name="exts" value="ebpextensions\statemodel_ext" List.ItemID="-125428134" List.ParentItemID="-125428134">
			<instance_reference name="schema" value="statemodel_schema\units\civilizations\ottoman\sipahi_ott" overrideParent="True" />
		</template_reference>
		<template_reference name="exts" value="ebpextensions\modifier_apply_ext" List.ItemID="-693874497" List.ListAction="Append">
			<list name="modifiers">
			</list>
		</template_reference>
	</list>
	<uniqueid name="pbgid" value="1073742543" />
	<instance_reference name="parent_pbg" value="ebps\races\core\units\unit_horseman_4" />
</instance>